LICENSE
README.md
legendkit/__init__.py
legendkit/_colorart.py
legendkit/_colorbar.py
legendkit/_handlers.py
legendkit/_legend.py
legendkit/_locs.py
legendkit/_register.py
legendkit/handles.py
legendkit/layout.py
pyproject.toml
legendkit-0.3.6.dist-info/METADATA
legendkit-0.3.6.dist-info/WHEEL
legendkit-0.3.6.dist-info/licenses/LICENSE
legendkit-0.3.6.dist-info/RECORD
