Metadata-Version: 2.4
Name: legendkit
Version: 0.3.6
Summary: Legend creation and manipulation with ease for matplotlib
Author-email: Mr-Milk <yzheng@cemm.at>
License: The MIT License (MIT)
License-File: LICENSE
Classifier: Framework :: Matplotlib
Classifier: Intended Audience :: Developers
Classifier: Intended Audience :: Science/Research
Classifier: License :: OSI Approved :: MIT License
Classifier: Programming Language :: Python :: 3
Classifier: Topic :: Scientific/Engineering :: Visualization
Requires-Python: >=3.8
Requires-Dist: matplotlib
